sssom_curator/.DS_Store
sssom_curator/__init__.py
sssom_curator/__main__.py
sssom_curator/cli.py
sssom_curator/constants.py
sssom_curator/export/__init__.py
sssom_curator/export/charts.py
sssom_curator/export/merge.py
sssom_curator/export/summary.py
sssom_curator/initialize/README.md.jinja2
sssom_curator/initialize/__init__.py
sssom_curator/initialize/cc0.txt
sssom_curator/initialize/main.py.jinja2
sssom_curator/predict/__init__.py
sssom_curator/predict/embedding.py
sssom_curator/predict/lexical.py
sssom_curator/predict/utils.py
sssom_curator/py.typed
sssom_curator/repository.py
sssom_curator/testing.py
sssom_curator/version.py
sssom_curator/web/__init__.py
sssom_curator/web/blueprint.py
sssom_curator/web/components.py
sssom_curator/web/impl.py
sssom_curator/web/templates/base.html
sssom_curator/web/templates/home.html
sssom_curator/web/templates/summary.html
sssom_curator/web/utils.py
sssom_curator-0.1.1.dist-info/licenses/LICENSE
sssom_curator-0.1.1.dist-info/WHEEL
sssom_curator-0.1.1.dist-info/entry_points.txt
sssom_curator-0.1.1.dist-info/METADATA
sssom_curator-0.1.1.dist-info/RECORD
