Metadata-Version: 2.4
Name: sssom-curator
Version: 0.1.1
Summary: Tools for predicting and curating semantic mappings
Keywords: snekpack,cookiecutter,sssom,semantic mappings,mapping alignment,ontology alignment,semantic web
Author: Charles Tapley Hoyt
Author-email: Charles Tapley Hoyt <cthoyt@gmail.com>
License-File: LICENSE
Classifier: Development Status :: 4 - Beta
Classifier: Environment :: Console
Classifier: Intended Audience :: Science/Research
Classifier: Intended Audience :: Developers
Classifier: License :: OSI Approved :: MIT License
Classifier: Operating System :: OS Independent
Classifier: Framework :: Pytest
Classifier: Framework :: tox
Classifier: Framework :: Sphinx
Classifier: Natural Language :: English
Classifier: Programming Language :: Python
Classifier: Programming Language :: Python :: 3.10
Classifier: Programming Language :: Python :: 3.11
Classifier: Programming Language :: Python :: 3.12
Classifier: Programming Language :: Python :: 3.13
Classifier: Programming Language :: Python :: 3 :: Only
Classifier: Typing :: Typed
Classifier: Topic :: Scientific/Engineering :: Chemistry
Classifier: Topic :: Scientific/Engineering :: Bio-Informatics
Requires-Dist: requests
Requires-Dist: click
Requires-Dist: pyyaml
Requires-Dist: tqdm
Requires-Dist: curies>=0.12.1
Requires-Dist: pystow>=0.7.11
Requires-Dist: bioregistry>=0.12.43
Requires-Dist: sssom-pydantic>=0.1.0
Requires-Dist: typing-extensions
Requires-Dist: jinja2
Requires-Dist: sssom ; extra == 'exports'
Requires-Dist: pandas ; extra == 'exports'
Requires-Dist: ndex2 ; extra == 'exports'
Requires-Dist: matplotlib ; extra == 'exports'
Requires-Dist: seaborn ; extra == 'exports'
Requires-Dist: networkx ; extra == 'exports'
Requires-Dist: sentence-transformers ; extra == 'predict-embeddings'
Requires-Dist: torch ; extra == 'predict-embeddings'
Requires-Dist: pandas ; extra == 'predict-embeddings'
Requires-Dist: pyobo[gilda-slim]>=0.12.11 ; extra == 'predict-lexical'
Requires-Dist: flask ; extra == 'web'
Requires-Dist: bootstrap-flask ; extra == 'web'
Requires-Dist: flask-wtf ; extra == 'web'
Maintainer: Charles Tapley Hoyt
Maintainer-email: Charles Tapley Hoyt <cthoyt@gmail.com>
Requires-Python: >=3.10
Project-URL: Bug Tracker, https://github.com/cthoyt/sssom-curator/issues
Project-URL: Documentation, https://sssom_curator.readthedocs.io
Project-URL: Funding, https://github.com/sponsors/cthoyt
Project-URL: Homepage, https://github.com/cthoyt/sssom-curator
Project-URL: Repository, https://github.com/cthoyt/sssom-curator.git
Provides-Extra: exports
Provides-Extra: predict-embeddings
Provides-Extra: predict-lexical
Provides-Extra: web
